{
  "run_id": "pmtrain-1781825288",
  "updated_at": 1781826702.772,
  "total_decisions": 143139620,
  "total_no_trade_labels": 141668172,
  "total_shadow_labels": 2258396,
  "total_pending_labels": 1560,
  "total_completed_labels": 1211,
  "feedback_per_hour": 916.4793,
  "labels_resolved_per_day": 21995.5034,
  "brier_after": 0.840159,
  "ece_after": null,
  "calibration_updates": 16,
  "category_reliability": {},
  "growth": {
    "learning_growth_score": 1.0,
    "learning_growth_status": "growing",
    "learning_growth_reason": "labels resolving into feedback + calibration updates"
  }
}