{"schema": "profitability_ranking/1.0", "paper_only": true, "profitability_first_enabled": true, "profitability_annotation_before_truncation": true, "require_profitability_annotation": true, "candidates_annotated": 22, "candidates_missing_profitability_data": 0, "candidates_ranked_by_profitability": 0, "candidates_rejected_negative_after_cost": 0, "candidates_shadow_theoretical_only": 0, "directional_after_cost_positive": 0, "bregman_after_cost_positive": 0, "exploration_profitability_checked": 22, "profitability_governor_hard_rejects": 0, "execution_without_annotation": 0, "avg_after_cost_edge_executed": 0.0, "avg_after_cost_roi_executed": 0.0, "total_expected_value_usd_executed": 0, "profitability_buckets": {"exploration_feedback_positive": 22}, "top_ranked_candidate_reason": "no after-cost-positive executable candidate this run", "bregman_first_priority_preserved": true, "learning_probe_quality_floor": 0.25, "top_opened_learning_probes": [{"market_id": "601826", "event_id": "event:45915", "category": "uncategorized", "question": "Will Fl\u00e1vio Bolsonaro win the 2026 Brazilian presidential election?", "reason": "passed_quality_floor", "probe_quality_score": 0.8909, "quality_components": {"edge_q": 1.0, "spread_q": 0.988, "depth_q": 1.0, "fresh_q": 0.82, "exec_q": 0.198, "al_q": 1.0, "grok_q": 1.0}, "after_cost_edge": 0.0, "spread": 0.001, "depth": 5.0, "book_age_sec": 3.59, "execution_quality": 0.1975, "active_learning_score": 1.905, "grok_supported": true, "ev_class": "near_zero_learning"}, {"market_id": "601826", "event_id": "event:45915", "category": "uncategorized", "question": "Will Fl\u00e1vio Bolsonaro win the 2026 Brazilian presidential election?", "reason": "passed_quality_floor", "probe_quality_score": 0.8909, "quality_components": {"edge_q": 1.0, "spread_q": 0.988, "depth_q": 1.0, "fresh_q": 0.82, "exec_q": 0.198, "al_q": 1.0, "grok_q": 1.0}, "after_cost_edge": 0.0, "spread": 0.001, "depth": 5.0, "book_age_sec": 3.59, "execution_quality": 0.1975, "active_learning_score": 1.905, "grok_supported": true, "ev_class": "near_zero_learning"}, {"market_id": "601826", "event_id": "event:45915", "category": "uncategorized", "question": "Will Fl\u00e1vio Bolsonaro win the 2026 Brazilian presidential election?", "reason": "passed_quality_floor", "probe_quality_score": 0.8909, "quality_components": {"edge_q": 1.0, "spread_q": 0.988, "depth_q": 1.0, "fresh_q": 0.82, "exec_q": 0.198, "al_q": 1.0, "grok_q": 1.0}, "after_cost_edge": 0.0, "spread": 0.001, "depth": 5.0, "book_age_sec": 3.59, "execution_quality": 0.1975, "active_learning_score": 1.8952, "grok_supported": true, "ev_class": "near_zero_learning"}, {"market_id": "601826", "event_id": "event:45915", "category": "uncategorized", "question": "Will Fl\u00e1vio Bolsonaro win the 2026 Brazilian presidential election?", "reason": "passed_quality_floor", "probe_quality_score": 0.8909, "quality_components": {"edge_q": 1.0, "spread_q": 0.988, "depth_q": 1.0, "fresh_q": 0.82, "exec_q": 0.198, "al_q": 1.0, "grok_q": 1.0}, "after_cost_edge": 0.0, "spread": 0.001, "depth": 5.0, "book_age_sec": 3.59, "execution_quality": 0.1975, "active_learning_score": 1.8952, "grok_supported": true, "ev_class": "near_zero_learning"}, {"market_id": "601826", "event_id": "event:45915", "category": "uncategorized", "question": "Will Fl\u00e1vio Bolsonaro win the 2026 Brazilian presidential election?", "reason": "passed_quality_floor", "probe_quality_score": 0.8909, "quality_components": {"edge_q": 1.0, "spread_q": 0.988, "depth_q": 1.0, "fresh_q": 0.82, "exec_q": 0.198, "al_q": 1.0, "grok_q": 1.0}, "after_cost_edge": 0.0, "spread": 0.001, "depth": 5.0, "book_age_sec": 3.59, "execution_quality": 0.1975, "active_learning_score": 1.8952, "grok_supported": true, "ev_class": "near_zero_learning"}, {"market_id": "2512444", "event_id": "event:585449", "category": "uncategorized", "question": "Will Benjamin Netanyahu sign a U.S. x Iran deal by July 31?", "reason": "passed_quality_floor", "probe_quality_score": 0.809, "quality_components": {"edge_q": 1.0, "spread_q": 0.975, "depth_q": 1.0, "fresh_q": 0.291, "exec_q": 0.195, "al_q": 0.998, "grok_q": 1.0}, "after_cost_edge": 0.0, "spread": 0.002, "depth": 5.0, "book_age_sec": 14.19, "execution_quality": 0.195, "active_learning_score": 0.9977, "grok_supported": true, "ev_class": "near_zero_learning"}, {"market_id": "2512444", "event_id": "event:585449", "category": "uncategorized", "question": "Will Benjamin Netanyahu sign a U.S. x Iran deal by July 31?", "reason": "passed_quality_floor", "probe_quality_score": 0.809, "quality_components": {"edge_q": 1.0, "spread_q": 0.975, "depth_q": 1.0, "fresh_q": 0.291, "exec_q": 0.195, "al_q": 0.998, "grok_q": 1.0}, "after_cost_edge": 0.0, "spread": 0.002, "depth": 5.0, "book_age_sec": 14.19, "execution_quality": 0.195, "active_learning_score": 0.9977, "grok_supported": true, "ev_class": "near_zero_learning"}, {"market_id": "2512444", "event_id": "event:585449", "category": "uncategorized", "question": "Will Benjamin Netanyahu sign a U.S. x Iran deal by July 31?", "reason": "passed_quality_floor", "probe_quality_score": 0.809, "quality_components": {"edge_q": 1.0, "spread_q": 0.975, "depth_q": 1.0, "fresh_q": 0.291, "exec_q": 0.195, "al_q": 0.998, "grok_q": 1.0}, "after_cost_edge": 0.0, "spread": 0.002, "depth": 5.0, "book_age_sec": 14.19, "execution_quality": 0.195, "active_learning_score": 0.9977, "grok_supported": true, "ev_class": "near_zero_learning"}, {"market_id": "2512444", "event_id": "event:585449", "category": "uncategorized", "question": "Will Benjamin Netanyahu sign a U.S. x Iran deal by July 31?", "reason": "passed_quality_floor", "probe_quality_score": 0.809, "quality_components": {"edge_q": 1.0, "spread_q": 0.975, "depth_q": 1.0, "fresh_q": 0.291, "exec_q": 0.195, "al_q": 0.998, "grok_q": 1.0}, "after_cost_edge": 0.0, "spread": 0.002, "depth": 5.0, "book_age_sec": 14.19, "execution_quality": 0.195, "active_learning_score": 0.9977, "grok_supported": true, "ev_class": "near_zero_learning"}, {"market_id": "2512444", "event_id": "event:585449", "category": "uncategorized", "question": "Will Benjamin Netanyahu sign a U.S. x Iran deal by July 31?", "reason": "passed_quality_floor", "probe_quality_score": 0.809, "quality_components": {"edge_q": 1.0, "spread_q": 0.975, "depth_q": 1.0, "fresh_q": 0.291, "exec_q": 0.195, "al_q": 0.998, "grok_q": 1.0}, "after_cost_edge": 0.0, "spread": 0.002, "depth": 5.0, "book_age_sec": 14.19, "execution_quality": 0.195, "active_learning_score": 0.9977, "grok_supported": true, "ev_class": "near_zero_learning"}, {"market_id": "2512444", "event_id": "event:585449", "category": "uncategorized", "question": "Will Benjamin Netanyahu sign a U.S. x Iran deal by July 31?", "reason": "passed_quality_floor", "probe_quality_score": 0.809, "quality_components": {"edge_q": 1.0, "spread_q": 0.975, "depth_q": 1.0, "fresh_q": 0.291, "exec_q": 0.195, "al_q": 0.998, "grok_q": 1.0}, "after_cost_edge": 0.0, "spread": 0.002, "depth": 5.0, "book_age_sec": 14.19, "execution_quality": 0.195, "active_learning_score": 0.9977, "grok_supported": true, "ev_class": "near_zero_learning"}, {"market_id": "2512444", "event_id": "event:585449", "category": "uncategorized", "question": "Will Benjamin Netanyahu sign a U.S. x Iran deal by July 31?", "reason": "passed_quality_floor", "probe_quality_score": 0.809, "quality_components": {"edge_q": 1.0, "spread_q": 0.975, "depth_q": 1.0, "fresh_q": 0.291, "exec_q": 0.195, "al_q": 0.998, "grok_q": 1.0}, "after_cost_edge": 0.0, "spread": 0.002, "depth": 5.0, "book_age_sec": 14.19, "execution_quality": 0.195, "active_learning_score": 0.9977, "grok_supported": true, "ev_class": "near_zero_learning"}, {"market_id": "2512444", "event_id": "event:585449", "category": "uncategorized", "question": "Will Benjamin Netanyahu sign a U.S. x Iran deal by July 31?", "reason": "passed_quality_floor", "probe_quality_score": 0.809, "quality_components": {"edge_q": 1.0, "spread_q": 0.975, "depth_q": 1.0, "fresh_q": 0.291, "exec_q": 0.195, "al_q": 0.998, "grok_q": 1.0}, "after_cost_edge": 0.0, "spread": 0.002, "depth": 5.0, "book_age_sec": 14.19, "execution_quality": 0.195, "active_learning_score": 0.9977, "grok_supported": true, "ev_class": "near_zero_learning"}, {"market_id": "2326497", "event_id": "event:511452", "category": "uncategorized", "question": "Netherlands vs. Sweden: Both Teams to Score", "reason": "passed_quality_floor", "probe_quality_score": 0.789, "quality_components": {"edge_q": 1.0, "spread_q": 0.875, "depth_q": 1.0, "fresh_q": 0.578, "exec_q": 0.175, "al_q": 0.69, "grok_q": 1.0}, "after_cost_edge": 0.0, "spread": 0.01, "depth": 5.0, "book_age_sec": 8.43, "execution_quality": 0.175, "active_learning_score": 0.6897, "grok_supported": true, "ev_class": "near_zero_learning"}, {"market_id": "2326497", "event_id": "event:511452", "category": "uncategorized", "question": "Netherlands vs. Sweden: Both Teams to Score", "reason": "passed_quality_floor", "probe_quality_score": 0.789, "quality_components": {"edge_q": 1.0, "spread_q": 0.875, "depth_q": 1.0, "fresh_q": 0.578, "exec_q": 0.175, "al_q": 0.69, "grok_q": 1.0}, "after_cost_edge": 0.0, "spread": 0.01, "depth": 5.0, "book_age_sec": 8.43, "execution_quality": 0.175, "active_learning_score": 0.6897, "grok_supported": true, "ev_class": "near_zero_learning"}, {"market_id": "2069649", "event_id": "event:413862", "category": "uncategorized", "question": "Will Deniz Undav be the top goalscorer at the 2026 FIFA World Cup?", "reason": "passed_quality_floor", "probe_quality_score": 0.7772, "quality_components": {"edge_q": 1.0, "spread_q": 0.963, "depth_q": 1.0, "fresh_q": 0.513, "exec_q": 0.193, "al_q": 0.577, "grok_q": 1.0}, "after_cost_edge": 0.0, "spread": 0.003, "depth": 5.0, "book_age_sec": 9.74, "execution_quality": 0.1925, "active_learning_score": 0.5773, "grok_supported": true, "ev_class": "near_zero_learning"}, {"market_id": "2069649", "event_id": "event:413862", "category": "uncategorized", "question": "Will Deniz Undav be the top goalscorer at the 2026 FIFA World Cup?", "reason": "passed_quality_floor", "probe_quality_score": 0.7772, "quality_components": {"edge_q": 1.0, "spread_q": 0.963, "depth_q": 1.0, "fresh_q": 0.513, "exec_q": 0.193, "al_q": 0.577, "grok_q": 1.0}, "after_cost_edge": 0.0, "spread": 0.003, "depth": 5.0, "book_age_sec": 9.74, "execution_quality": 0.1925, "active_learning_score": 0.5773, "grok_supported": true, "ev_class": "near_zero_learning"}, {"market_id": "2069649", "event_id": "event:413862", "category": "uncategorized", "question": "Will Deniz Undav be the top goalscorer at the 2026 FIFA World Cup?", "reason": "passed_quality_floor", "probe_quality_score": 0.7772, "quality_components": {"edge_q": 1.0, "spread_q": 0.963, "depth_q": 1.0, "fresh_q": 0.513, "exec_q": 0.193, "al_q": 0.577, "grok_q": 1.0}, "after_cost_edge": 0.0, "spread": 0.003, "depth": 5.0, "book_age_sec": 9.74, "execution_quality": 0.1925, "active_learning_score": 0.5773, "grok_supported": true, "ev_class": "near_zero_learning"}, {"market_id": "2069649", "event_id": "event:413862", "category": "uncategorized", "question": "Will Deniz Undav be the top goalscorer at the 2026 FIFA World Cup?", "reason": "passed_quality_floor", "probe_quality_score": 0.7772, "quality_components": {"edge_q": 1.0, "spread_q": 0.963, "depth_q": 1.0, "fresh_q": 0.513, "exec_q": 0.193, "al_q": 0.577, "grok_q": 1.0}, "after_cost_edge": 0.0, "spread": 0.003, "depth": 5.0, "book_age_sec": 9.74, "execution_quality": 0.1925, "active_learning_score": 0.5773, "grok_supported": true, "ev_class": "near_zero_learning"}, {"market_id": "2069649", "event_id": "event:413862", "category": "uncategorized", "question": "Will Deniz Undav be the top goalscorer at the 2026 FIFA World Cup?", "reason": "passed_quality_floor", "probe_quality_score": 0.7772, "quality_components": {"edge_q": 1.0, "spread_q": 0.963, "depth_q": 1.0, "fresh_q": 0.513, "exec_q": 0.193, "al_q": 0.577, "grok_q": 1.0}, "after_cost_edge": 0.0, "spread": 0.003, "depth": 5.0, "book_age_sec": 9.74, "execution_quality": 0.1925, "active_learning_score": 0.5773, "grok_supported": true, "ev_class": "near_zero_learning"}, {"market_id": "1892311", "event_id": "event:350795", "category": "uncategorized", "question": "Will FURIA win IEM Cologne Major 2026?", "reason": "passed_quality_floor", "probe_quality_score": 0.7247, "quality_components": {"edge_q": 1.0, "spread_q": 0.963, "depth_q": 1.0, "fresh_q": 0.034, "exec_q": 0.193, "al_q": 0.707, "grok_q": 1.0}, "after_cost_edge": 0.0, "spread": 0.003, "depth": 5.0, "book_age_sec": 19.31, "execution_quality": 0.1925, "active_learning_score": 0.7065, "grok_supported": true, "ev_class": "near_zero_learning"}, {"market_id": "679034", "event_id": "event:79987", "category": "uncategorized", "question": "Will Dominique de Villepin win the 2027 French presidential election?", "reason": "passed_quality_floor", "probe_quality_score": 0.6946, "quality_components": {"edge_q": 1.0, "spread_q": 0.988, "depth_q": 1.0, "fresh_q": 0.068, "exec_q": 0.198, "al_q": 0.443, "grok_q": 1.0}, "after_cost_edge": 0.0, "spread": 0.001, "depth": 5.0, "book_age_sec": 18.63, "execution_quality": 0.1975, "active_learning_score": 0.443, "grok_supported": true, "ev_class": "near_zero_learning"}], "top_rejected_near_misses": [], "opened_learning_probes_count": 22, "rejected_learning_probes_count": 0, "thresholds": {"min_after_cost_edge": 0.01, "min_after_cost_roi": 0.002, "min_expected_value_usd": 0.01, "bregman_min_after_cost_profit_usd": 0.02}}